[
  {
    "title": "Reflection Enabler",
    "description": "Stay on track with your goals and aspirations.",
    "image": {
      "url": "images/features/noun_branding_1885335.svg",
      "width": 80,
      "height": 80
    }
  },
  {
    "title": "Reflection Tracker",
    "description": "Track your progress and see how far you've come.",
    "image": {
      "url": "images/features/noun_The Process_1885341.svg",
      "width": 80,
      "height": 80
    }
  },
  {
    "title": "Reflection Helper",
    "description": "Options to get AI help with your reflections.",
    "image": {
      "url": "images/features/noun_3d modeling_1885342.svg",
      "width": 80,
      "height": 80
    }
  }
]
